README.rst
setup.cfg
setup.py
csdaily/__init__.py
csdaily/__version__.py
csdaily.egg-info/PKG-INFO
csdaily.egg-info/SOURCES.txt
csdaily.egg-info/dependency_links.txt
csdaily.egg-info/entry_points.txt
csdaily.egg-info/not-zip-safe
csdaily.egg-info/top_level.txt