Metadata-Version: 1.2
Name: csdaily
Version: 0.1
Summary: China Stock Daily
Home-page: https://github.com/qytz/cn_stock_daily
Author: qytz
Author-email: hhhhhf@foxmail.com
License: Apache License 2.0
Platform: UNKNOWN
Classifier: Development Status :: 2 - Pre-Alpha
Classifier: Intended Audience :: Developers
Classifier: License :: OSI Approved :: Apache Software License
Classifier: Programming Language :: Python :: 3
Classifier: Programming Language :: Python :: 3.5
Classifier: Programming Language :: Python :: 3.6
Requires-Python: >=3.5
